libp/__init__.py
libp-1.0.0.dist-info/WHEEL
libp-1.0.0.dist-info/METADATA
libp-1.0.0.dist-info/RECORD
