Metadata-Version: 2.1
Name: libp
Version: 1.0.0
Summary: libp
License: MIT
Author: Ardustri
Author-email: contact@ardustri.org
Requires-Python: >=3.7
Classifier: License :: OSI Approved :: MIT License
Classifier: Programming Language :: Python :: 3
Classifier: Programming Language :: Python :: 3.7
Classifier: Programming Language :: Python :: 3.8
Classifier: Programming Language :: Python :: 3.9
